[
  {
    "ContainingType": "StudentMgmtSystem.Controllers.AuthController",
    "Method": "GenerateOtp",
    "RelativePath": "api/auth/generate-otp",
    "HttpMethod": "POST",
    "IsController": true,
    "Order": 0,
    "Parameters": [
      {
        "Name": "req",
        "Type": "StudentMgmtSystem.Models.Request.Auth.OtpRequest",
        "IsRequired": true
      }
    ],
    "ReturnTypes": []
  },
  {
    "ContainingType": "StudentMgmtSystem.Controllers.AuthController",
    "Method": "Login",
    "RelativePath": "api/auth/login",
    "HttpMethod": "POST",
    "IsController": true,
    "Order": 0,
    "Parameters": [
      {
        "Name": "req",
        "Type": "StudentMgmtSystem.Models.Request.Auth.LoginRequest",
        "IsRequired": true
      }
    ],
    "ReturnTypes": []
  },
  {
    "ContainingType": "StudentMgmtSystem.Controllers.AuthController",
    "Method": "Register",
    "RelativePath": "api/auth/register",
    "HttpMethod": "POST",
    "IsController": true,
    "Order": 0,
    "Parameters": [
      {
        "Name": "req",
        "Type": "StudentMgmtSystem.Models.Request.Auth.RegisterRequest",
        "IsRequired": true
      }
    ],
    "ReturnTypes": []
  },
  {
    "ContainingType": "StudentMgmtSystem.Controllers.CourseController",
    "Method": "GetCourses",
    "RelativePath": "api/courses",
    "HttpMethod": "GET",
    "IsController": true,
    "Order": 0,
    "Parameters": [],
    "ReturnTypes": []
  },
  {
    "ContainingType": "StudentMgmtSystem.Controllers.CourseController",
    "Method": "CreateCourse",
    "RelativePath": "api/courses",
    "HttpMethod": "POST",
    "IsController": true,
    "Order": 0,
    "Parameters": [
      {
        "Name": "request",
        "Type": "StudentMgmtSystem.Models.Request.CourseRequest",
        "IsRequired": true
      }
    ],
    "ReturnTypes": []
  },
  {
    "ContainingType": "StudentMgmtSystem.Controllers.StudentsController",
    "Method": "Get",
    "RelativePath": "api/students",
    "HttpMethod": "GET",
    "IsController": true,
    "Order": 0,
    "Parameters": [],
    "ReturnTypes": []
  },
  {
    "ContainingType": "StudentMgmtSystem.Controllers.StudentsController",
    "Method": "Create",
    "RelativePath": "api/students",
    "HttpMethod": "POST",
    "IsController": true,
    "Order": 0,
    "Parameters": [
      {
        "Name": "request",
        "Type": "StudentMgmtSystem.Models.Request.StudentRequest",
        "IsRequired": true
      }
    ],
    "ReturnTypes": []
  }
]